poeminv/__init__.py
poeminv/config.py
poeminv/emission.py
poeminv/event.py
poeminv/util.py
poeminv-1.1.0.dist-info/LICENSE
poeminv-1.1.0.dist-info/METADATA
poeminv-1.1.0.dist-info/WHEEL
poeminv-1.1.0.dist-info/top_level.txt
poeminv-1.1.0.dist-info/RECORD
